pangumd.py
pangumd-0.1.4.dist-info/METADATA
pangumd-0.1.4.dist-info/WHEEL
pangumd-0.1.4.dist-info/entry_points.txt
pangumd-0.1.4.dist-info/top_level.txt
pangumd-0.1.4.dist-info/RECORD
