Metadata-Version: 2.4
Name: pangumd
Version: 0.1.4
Summary: Intelligently adds spacing between CJK and alphanumeric characters with special handling for Markdown.
Author-email: kingronjan <kingronjan@qq.com>
License: MIT
Project-URL: Homepage, https://github.com/kingronjan/pangumd
Project-URL: Repository, https://github.com/kingronjan/pangumd
Project-URL: Bug Tracker, https://github.com/kingronjan/pangumd/issues
Classifier: Development Status :: 4 - Beta
Classifier: Intended Audience :: Developers
Classifier: License :: OSI Approved :: MIT License
Classifier: Operating System :: OS Independent
Classifier: Programming Language :: Python :: 3
Classifier: Programming Language :: Python :: 3.13
Classifier: Topic :: Software Development :: Libraries :: Python Modules
Classifier: Topic :: Text Processing
Requires-Python: >=3.13
Requires-Dist: marko>=2.2.2
Requires-Dist: pangu>=4.0.6.1
